s3_tool/__init__.py
s3_tool/s3_tool.py
ha_s3_tool-0.1.2.dist-info/METADATA
ha_s3_tool-0.1.2.dist-info/WHEEL
ha_s3_tool-0.1.2.dist-info/entry_points.txt
ha_s3_tool-0.1.2.dist-info/top_level.txt
ha_s3_tool-0.1.2.dist-info/RECORD
