Metadata-Version: 2.1
Name: ha-s3-tool
Version: 0.1.2
Summary: A tool for uploading and downloading files and folders to/from S3.
Home-page: https://github.com/manuelladron/s3_tool
Author: Manuel Rodriguez Ladron de Guevara
Author-email: manuelrodriguez@higharc.com
Classifier: Programming Language :: Python :: 3
Classifier: License :: OSI Approved :: MIT License
Classifier: Operating System :: OS Independent
Requires-Python: >=3.6
Requires-Dist: boto3
Requires-Dist: tqdm
